test_python_sdk/__init__.py
test_python_sdk/api_client/__init__.py
test_python_sdk/api_client/execute.py
test_python_sdk/api_client/query.py
test_python_sdk/api_client/types/__init__.py
test_python_sdk/api_client/types/eip712order.py
test_python_sdk/api_client/types/execute.py
test_python_sdk/api_client/types/models.py
test_python_sdk/api_client/types/query.py
test_python_sdk/client/__init__.py
test_python_sdk/client/context.py
test_python_sdk/contracts/__init__.py
test_python_sdk/contracts/abis/AccountBalance.json
test_python_sdk/contracts/abis/CollateralManager.json
test_python_sdk/contracts/abis/ERC20.json
test_python_sdk/contracts/abis/FundingRate.json
test_python_sdk/contracts/abis/MatchingEngine.json
test_python_sdk/contracts/abis/Periphery.json
test_python_sdk/contracts/abis/PerpView.json
test_python_sdk/contracts/abis/PerpetualOracle.json
test_python_sdk/contracts/abis/Positioning.json
test_python_sdk/contracts/abis/PositioningConfig.json
test_python_sdk/contracts/abis/QuoteToken.json
test_python_sdk/contracts/abis/Vault.json
test_python_sdk/contracts/deployments/volmex-chain-testnet/baseTokens.json
test_python_sdk/contracts/deployments/volmex-chain-testnet/collateral.json
test_python_sdk/contracts/deployments/volmex-chain-testnet/contracts.json
test_python_sdk/contracts/deployments/volmex-chain-testnet/urls.json
test_python_sdk/contracts/loader.py
test_python_sdk/contracts/types.py
test_python_sdk/utils/__init__.py
test_python_sdk/utils/enum.py
test_python_sdk/utils/exceptions.py
test_python_sdk/utils/math.py
test_python_sdk/utils/model.py
test_python_sdk/utils/order.py
test_python_sdk/utils/signed_message_to_str.py
test_python_sdk/utils/status_codes.py
test_python_sdk-0.1.0.dist-info/METADATA
test_python_sdk-0.1.0.dist-info/WHEEL
test_python_sdk-0.1.0.dist-info/entry_points.txt
test_python_sdk-0.1.0.dist-info/RECORD
